upstream_ontologist/guess.py
upstream_ontologist/_upstream_ontologist.cpython-313-darwin.so
upstream_ontologist/__init__.py
upstream_ontologist/vcs.py
upstream_ontologist/py.typed
upstream_ontologist/_upstream_ontologist.pyi
upstream_ontologist/.dylibs/libssl.3.dylib
upstream_ontologist/.dylibs/libcrypto.3.dylib
upstream_ontologist-0.2.7.dist-info/RECORD
upstream_ontologist-0.2.7.dist-info/WHEEL
upstream_ontologist-0.2.7.dist-info/top_level.txt
upstream_ontologist-0.2.7.dist-info/METADATA
